dist_meta/__init__.py
dist_meta/core.py
dist_meta/scripts.py
ud_dist_meta-1.0.3.dist-info/LICENSE
ud_dist_meta-1.0.3.dist-info/METADATA
ud_dist_meta-1.0.3.dist-info/WHEEL
ud_dist_meta-1.0.3.dist-info/entry_points.txt
ud_dist_meta-1.0.3.dist-info/top_level.txt
ud_dist_meta-1.0.3.dist-info/RECORD
