Metadata-Version: 2.1
Name: ud-dist-meta
Version: 1.0.3
Summary: Library to extract information from packages installed in current python environment
Home-page: https://github.com/um-en/ud-dist-meta
Author: Umbriel Draken
Author-email: umbriel.draken@gmail.com
License: MIT
Keywords: distribution,virtual environment,metadata
Platform: UNKNOWN
Classifier: License :: OSI Approved :: MIT License
Classifier: Programming Language :: Python :: 3.9
Classifier: Development Status :: 3 - Alpha
Classifier: Intended Audience :: Developers
Classifier: Natural Language :: English
Classifier: Operating System :: Microsoft :: Windows :: Windows 10
Requires-Dist: importlib-metadata
Requires-Dist: pyyaml
